pychatter/__init__.py
pychatter/__main__.py
pychatter/cli.py
pychatter/py.typed
pychatter/run_server.py
pychatter/gui/__init__.py
pychatter/gui/callbacks.py
pychatter/gui/components.py
pychatter/gui/config.py
pychatter/gui/init.py
pychatter/gui/text.py
pychatter/network/__init__.py
pychatter/network/cleanup.py
pychatter/network/client.py
pychatter/network/config.py
pychatter/network/server.py
pychatter/network/util.py
pychatter-0.1.3.dist-info/LICENSE
pychatter-0.1.3.dist-info/METADATA
pychatter-0.1.3.dist-info/WHEEL
pychatter-0.1.3.dist-info/top_level.txt
pychatter-0.1.3.dist-info/RECORD
