Metadata-Version: 2.1
Name: pychatter
Version: 0.1.3
Summary: Local network chat messaging application
Home-page: https://github.com/rbaltrusch/pychatter
Author: Richard Baltrusch
License: MIT
Keywords: python
Classifier: Development Status :: 4 - Beta
Classifier: Intended Audience :: Developers
Classifier: Intended Audience :: End Users/Desktop
Classifier: License :: OSI Approved :: MIT License
Classifier: Programming Language :: Python
Classifier: Programming Language :: Python :: 3
Classifier: Programming Language :: Python :: 3 :: Only
Classifier: Programming Language :: Python :: 3.8
Classifier: Programming Language :: Python :: 3.9
Classifier: Programming Language :: Python :: 3.10
Classifier: Programming Language :: Python :: 3.11
Classifier: Typing :: Typed
Classifier: Topic :: Communications :: Chat
Requires-Python: >=3.8
License-File: LICENSE
